sndfileio/__init__.py
sndfileio/backend_lameenc.py
sndfileio/backend_miniaudio.py
sndfileio/datastructs.py
sndfileio/dsp.py
sndfileio/mp3.py
sndfileio/py.typed
sndfileio/resampling.py
sndfileio/sndfileio.py
sndfileio/testing.py
sndfileio/util.py
sndfileio/testfiles/M1F1-float32-format-extensible-stereo.wav
sndfileio/testfiles/M1F1-float32-stereo.wav
sndfileio/testfiles/M1F1-int24-format-extensible-stereo.wav
sndfileio/testfiles/M1F1-int24-mono.wav
sndfileio/testfiles/stereo-float32.aif
sndfileio/testfiles/stereo-int32.aif
sndfileio/testfiles/stereofl32.wav
sndfileio-2.1.2.dist-info/licenses/LICENSE.md
sndfileio-2.1.2.dist-info/METADATA
sndfileio-2.1.2.dist-info/WHEEL
sndfileio-2.1.2.dist-info/top_level.txt
sndfileio-2.1.2.dist-info/RECORD
