Metadata-Version: 2.4
Name: sndfileio
Version: 2.1.2
Summary: Simple API for reading / writing soundfiles
Author-email: Eduardo Moguillansky <eduardo.moguillansky@gmail.com>
License: Copyright (c) 2011-2017 GitHub Inc.
Project-URL: Homepage, https://github.com/gesellkammer/sndfileio
Classifier: Programming Language :: Python :: 3
Classifier: Operating System :: OS Independent
Requires-Python: >=3.10
License-File: LICENSE.md
Requires-Dist: numpy>1.8
Requires-Dist: scipy
Requires-Dist: soundfile
Requires-Dist: nnresample
Requires-Dist: numpyx>=0.4.1
Requires-Dist: tinytag
Requires-Dist: filetype
Requires-Dist: lameenc
Dynamic: license-file
